lisaorbits/__init__.py
lisaorbits/file.py
lisaorbits/oem.py
lisaorbits/orbits.py
lisaorbits/utils.py
lisaorbits-3.0.2.dist-info/METADATA
lisaorbits-3.0.2.dist-info/WHEEL
lisaorbits-3.0.2.dist-info/licenses/LICENSE
lisaorbits-3.0.2.dist-info/RECORD
