Metadata-Version: 2.4
Name: lisaorbits
Version: 3.0.2
Summary: Computes LISA spacecraft state vectors, light travel times and proper pseudoranges
License: BSD 3-Clause
License-File: LICENSE
Keywords: LISA,simulation
Author: Jean-Baptiste Bayle
Author-email: j2b.bayle@gmail.com>
Maintainer: Jean-Baptiste Bayle
Maintainer-email: j2b.bayle@gmail.com>
Requires-Python: >=3.12,<4
Classifier: Intended Audience :: Science/Research
Classifier: Topic :: Scientific/Engineering :: Astronomy
Classifier: Topic :: Scientific/Engineering :: Physics
Requires-Dist: astropy (>=6.1.4,<7.0.0)
Requires-Dist: attrs (>=25.3.0,<26.0.0)
Requires-Dist: h5py (>=3.12.1,<4.0.0)
Requires-Dist: importlib-metadata (>=8.5.0,<9.0.0)
Requires-Dist: lisaconstants (>=2.0.1,<3.0.0)
Requires-Dist: matplotlib (>=3.9.2,<4.0.0)
Requires-Dist: numpy (>=2.1.1,<3.0.0)
Requires-Dist: oem (>=0.4.2,<0.5.0)
Requires-Dist: pooch (>=1.8.2,<2.0.0)
Requires-Dist: scipy (>=1.14.1,<2.0.0)
Project-URL: Documentation, https://lisa-simulation.pages.in2p3.fr/orbits
Project-URL: Download, https://gitlab.in2p3.fr/lisa-simulation/orbits/-/releases
Project-URL: Issue Tracker, https://gitlab.in2p3.fr/lisa-simulation/orbits/-/issues
Project-URL: Repository, https://gitlab.in2p3.fr/lisa-simulation/orbits
